Topsis/__init__.py
Topsis/__main__.py
topsis_taanisha_10210323-1.1.2.dist-info/LICENSE
topsis_taanisha_10210323-1.1.2.dist-info/METADATA
topsis_taanisha_10210323-1.1.2.dist-info/WHEEL
topsis_taanisha_10210323-1.1.2.dist-info/entry_points.txt
topsis_taanisha_10210323-1.1.2.dist-info/top_level.txt
topsis_taanisha_10210323-1.1.2.dist-info/RECORD
