Metadata-Version: 2.1
Name: topsis-taanisha-10210323
Version: 1.1.2
Summary: TOPSIS implementation by Divyam Malik
Home-page: https://github.com/taanisha/topsis-taanisha-102103123
Author: Taanisha Agarwal
Author-email: taanisha777@gmail.com
License: MIT
Classifier: License :: OSI Approved :: MIT License
Classifier: Programming Language :: Python :: 3.6
Classifier: Programming Language :: Python :: 3.7
Classifier: Programming Language :: Python :: 3.8
License-File: LICENSE
Requires-Dist: numpy
Requires-Dist: pandas
